{"setup": {"name": "baQzZ", "count": 1, "horizon": 5, "seed": null, "no_hit": true, "start_with_tr": true, "first_tr": true}, "info": {"season": "2019-20", "gw": 24}, "output": {"total": 490, "initial": [191, 198, 93, 362, 181, 147, 393, 340, 488, 104, 122, 142, 160, 410, 618], "fixed": [340, 181], "solution": [{"gw": 24, "squad": [191, 198, 93, 362, 181, 147, 393, 340, 488, 104, 122, 142, 160, 410, 618], "lineup": [191, 93, 181, 147, 393, 488, 104, 122, 142, 160, 618], "cap": [181], "tr_in": [], "tr_out": [], "itb": 1.6, "ft": 0, "ln_pts": [16, 10, 7, 5, 3, 2, 1, 1, 1, 1, 0], "gw_pts": 54}, {"gw": 25, "squad": [191, 198, 93, 362, 181, 147, 393, 340, 488, 104, 122, 142, 160, 410, 618], "lineup": [191, 198, 362, 181, 393, 340, 104, 122, 142, 160, 618], "cap": [393], "tr_in": [], "tr_out": [], "itb": 1.6, "ft": 1, "ln_pts": [16, 13, 5, 6, 18, 15, 16, 9, 15, 6, 2], "gw_pts": 139}, {"gw": 26, "squad": [191, 198, 93, 362, 181, 147, 393, 340, 488, 122, 142, 160, 401, 410, 618], "lineup": [191, 198, 362, 181, 147, 340, 488, 122, 160, 401, 618], "cap": [488], "tr_in": [401], "tr_out": [104], "itb": 1.0, "ft": 2, "ln_pts": [3, 7, 2, 9, 11, 2, 17, 10, 15, 6, 6], "gw_pts": 105}, {"gw": 27, "squad": [191, 198, 93, 362, 147, 393, 340, 488, 122, 160, 401, 410, 103, 123, 618], "lineup": [191, 93, 147, 393, 122, 160, 401, 410, 103, 123, 618], "cap": [410], "tr_in": [103, 123], "tr_out": [181, 142], "itb": 1.6, "ft": 2, "ln_pts": [7, 9, 6, 5, 6, 6, 10, 16, 8, 15, 14], "gw_pts": 118}, {"gw": 28, "squad": [191, 198, 93, 362, 147, 340, 488, 122, 160, 401, 410, 103, 123, 525, 618], "lineup": [191, 93, 362, 147, 122, 401, 410, 103, 123, 525, 618], "cap": [525], "tr_in": [525], "tr_out": [393], "itb": 0.7, "ft": 1, "ln_pts": [2, 10, 11, 7, 2, 12, 12, 16, 8, 19, 10], "gw_pts": 128}]}}