{"setup": {"name": "EBMSP", "count": 1, "horizon": 5, "seed": null, "no_hit": true, "start_with_tr": true, "first_tr": false}, "info": {"season": "2016-17", "gw": 18}, "output": {"total": 503, "initial": [398, 123, 78, 125, 126, 354, 403, 12, 155, 438, 446, 33, 165, 49, 536], "fixed": [354, 49], "solution": [{"gw": 18, "squad": [398, 123, 78, 125, 126, 354, 403, 12, 155, 438, 446, 33, 165, 49, 536], "lineup": [398, 123, 78, 125, 403, 12, 155, 438, 446, 33, 536], "cap": [398], "tr_in": [], "tr_out": [], "itb": 3.1, "ft": 0, "ln_pts": [15, 12, 7, 6, 4, 3, 2, 2, 2, 1, 0], "gw_pts": 69}, {"gw": 19, "squad": [398, 123, 68, 78, 125, 126, 403, 12, 155, 438, 446, 33, 165, 49, 536], "lineup": [398, 68, 78, 125, 403, 12, 155, 446, 33, 165, 536], "cap": [68], "tr_in": [68], "tr_out": [354], "itb": 2.2, "ft": 1, "ln_pts": [14, 17, 7, 7, 16, 6, 10, 13, 12, 8, 8], "gw_pts": 135}, {"gw": 20, "squad": [398, 123, 68, 78, 125, 126, 403, 12, 155, 438, 446, 33, 165, 49, 536], "lineup": [398, 123, 125, 126, 12, 155, 438, 446, 33, 49, 536], "cap": [125], "tr_in": [], "tr_out": [], "itb": 2.2, "ft": 1, "ln_pts": [15, 7, 15, 6, 7, 10, 8, 9, 11, 6, 13], "gw_pts": 122}, {"gw": 21, "squad": [398, 123, 468, 68, 78, 125, 126, 561, 403, 12, 155, 438, 446, 165, 536], "lineup": [398, 123, 468, 78, 125, 126, 561, 403, 12, 155, 536], "cap": [561], "tr_in": [468, 561], "tr_out": [33, 49], "itb": 0.6, "ft": 2, "ln_pts": [6, 8, 5, 6, 6, 12, 21, 17, 11, 5, 4], "gw_pts": 122}, {"gw": 22, "squad": [123, 209, 468, 68, 78, 125, 126, 561, 403, 12, 155, 438, 446, 165, 536], "lineup": [123, 209, 468, 68, 78, 125, 126, 561, 403, 12, 438], "cap": [78], "tr_in": [209], "tr_out": [398], "itb": 1.2, "ft": 1, "ln_pts": [6, 14, 13, 8, 15, 6, 15, 6, 5, 8, 13], "gw_pts": 124}]}}