{"setup": {"name": "PI95G", "count": 1, "horizon": 5, "seed": null, "no_hit": true}, "info": {"season": "2020-21", "gw": 31}, "output": {"total": 437, "initial": [301, 233, 315, 155, 597, 91, 150, 322, 549, 89, 219, 498, 81, 157, 437], "fixed": [301], "solution": [{"gw": 31, "squad": [301, 233, 315, 155, 597, 91, 150, 322, 549, 89, 219, 498, 81, 157, 437], "lineup": [233, 315, 155, 597, 91, 150, 322, 89, 219, 498, 81], "cap": [597], "tr_in": [], "tr_out": [], "itb": 13.0, "ft": 0, "ln_pts": [13, 11, 6, 6, 5, 3, 2, 2, 1, 1, 1], "gw_pts": 57}, {"gw": 32, "squad": [301, 233, 315, 155, 597, 91, 150, 322, 549, 89, 219, 498, 81, 157, 437], "lineup": [301, 233, 315, 597, 150, 322, 549, 89, 219, 498, 81], "cap": [315], "tr_in": [], "tr_out": [], "itb": 13.0, "ft": 1, "ln_pts": [7, 6, 15, 9, 15, 10, 10, 5, 15, 11, 6], "gw_pts": 124}, {"gw": 33, "squad": [233, 315, 390, 155, 597, 91, 150, 322, 549, 89, 219, 498, 81, 157, 437], "lineup": [233, 315, 155, 91, 150, 549, 89, 219, 498, 81, 157], "cap": [91], "tr_in": [390], "tr_out": [301], "itb": 10.0, "ft": 2, "ln_pts": [12, 3, 6, 20, 3, 7, 9, 5, 9, 5, 9], "gw_pts": 108}, {"gw": 34, "squad": [233, 500, 390, 155, 597, 91, 322, 549, 89, 219, 498, 543, 81, 157, 437], "lineup": [233, 500, 390, 155, 597, 91, 322, 219, 498, 543, 437], "cap": [543], "tr_in": [500, 543], "tr_out": [315, 150], "itb": 6.6, "ft": 2, "ln_pts": [5, 16, 12, 7, 6, 6, 2, 10, 2, 21, 13], "gw_pts": 121}, {"gw": 35, "squad": [233, 500, 390, 155, 597, 91, 322, 549, 89, 219, 506, 498, 543, 81, 157], "lineup": [233, 390, 155, 91, 322, 549, 89, 506, 543, 81, 157], "cap": [506], "tr_in": [506], "tr_out": [437], "itb": 6.8, "ft": 1, "ln_pts": [2, 7, 6, 6, 8, 2, 10, 13, 2, 9, 6], "gw_pts": 84}]}}