{"setup": {"name": "us6ip", "count": 1, "horizon": 5, "seed": null, "no_hit": true, "start_with_tr": true, "first_tr": true}, "info": {"season": "2019-20", "gw": 23}, "output": {"total": 490, "initial": [182, 147, 172, 191, 393, 198, 342, 168, 411, 122, 159, 2, 92, 257, 410], "fixed": [411, 92], "solution": [{"gw": 23, "squad": [182, 147, 172, 191, 393, 198, 342, 168, 411, 122, 159, 2, 92, 257, 410], "lineup": [182, 147, 172, 191, 393, 198, 411, 2, 92, 257, 410], "cap": [393], "tr_in": [], "tr_out": [], "itb": 4.9, "ft": 0, "ln_pts": [10, 8, 7, 7, 5, 3, 2, 0, 0, 0, 0], "gw_pts": 47}, {"gw": 24, "squad": [182, 147, 172, 191, 393, 198, 342, 168, 411, 122, 159, 2, 92, 257, 410], "lineup": [182, 147, 172, 191, 393, 198, 342, 411, 159, 2, 257], "cap": [191], "tr_in": [], "tr_out": [], "itb": 4.9, "ft": 1, "ln_pts": [12, 5, 12, 16, 3, 16, 7, 2, 12, 8, 14], "gw_pts": 123}, {"gw": 25, "squad": [182, 147, 172, 191, 393, 198, 342, 104, 168, 411, 122, 159, 2, 92, 410], "lineup": [182, 172, 191, 393, 198, 342, 104, 411, 122, 2, 410], "cap": [393], "tr_in": [104], "tr_out": [257], "itb": 3.3, "ft": 2, "ln_pts": [6, 7, 16, 18, 13, 8, 16, 8, 9, 8, 2], "gw_pts": 129}, {"gw": 26, "squad": [182, 147, 191, 393, 198, 342, 168, 411, 488, 122, 159, 160, 2, 92, 410], "lineup": [182, 147, 198, 342, 411, 488, 122, 159, 160, 2, 92], "cap": [488], "tr_in": [488, 160], "tr_out": [172, 104], "itb": 0.8, "ft": 2, "ln_pts": [7, 11, 7, 13, 10, 17, 10, 6, 15, 6, 9], "gw_pts": 128}, {"gw": 27, "squad": [182, 147, 191, 393, 198, 342, 168, 411, 488, 122, 159, 160, 92, 123, 410], "lineup": [182, 147, 191, 393, 168, 488, 122, 160, 92, 123, 410], "cap": [410], "tr_in": [123], "tr_out": [2], "itb": 0.4, "ft": 1, "ln_pts": [10, 6, 7, 5, 12, 5, 6, 6, 6, 15, 16], "gw_pts": 110}]}}