[{"code": 2128328, "event": 5, "finished": true, "finished_provisional": true, "id": 41, "kickoff_time": "2020-10-17T11:30:00Z", "minutes": 90, "provisional_start_time": false, "started": true, "team_a": 11, "team_a_score": 2, "team_h": 7, "team_h_score": 2, "stats": [{"identifier": "goals_scored", "a": [{"value": 1, "element": 251}, {"value": 1, "element": 254}], "h": [{"value": 1, "element": 156}, {"value": 1, "element": 164}]}, {"identifier": "assists", "a": [{"value": 1, "element": 255}], "h": [{"value": 1, "element": 155}, {"value": 1, "element": 508}]}, {"identifier": "own_goals", "a": [], "h": []}, {"identifier": "penalties_saved", "a": [], "h": []}, {"identifier": "penalties_missed", "a": [], "h": []}, {"identifier": "yellow_cards", "a": [{"value": 1, "element": 251}, {"value": 1, "element": 253}], "h": [{"value": 1, "element": 158}, {"value": 1, "element": 502}, {"value": 1, "element": 508}]}, {"identifier": "red_cards", "a": [], "h": [{"value": 1, "element": 166}]}, {"identifier": "saves", "a": [{"value": 3, "element": 245}], "h": [{"value": 6, "element": 157}]}, {"identifier": "bonus", "a": [{"value": 2, "element": 255}], "h": [{"value": 3, "element": 155}, {"value": 1, "element": 156}]}, {"identifier": "bps", "a": [{"value": 33, "element": 255}, {"value": 24, "element": 254}, {"value": 19, "element": 531}, {"value": 18, "element": 251}, {"value": 14, "element": 245}, {"value": 14, "element": 259}, {"value": 12, "element": 260}, {"value": 10, "element": 246}, {"value": 9, "element": 244}, {"value": 9, "element": 253}, {"value": 8, "element": 249}, {"value": 5, "element": 468}, {"value": 3, "element": 243}], "h": [{"value": 34, "element": 155}, {"value": 28, "element": 156}, {"value": 22, "element": 508}, {"value": 21, "element": 157}, {"value": 21, "element": 164}, {"value": 9, "element": 512}, {"value": 8, "element": 566}, {"value": 6, "element": 162}, {"value": 3, "element": 152}, {"value": 3, "element": 159}, {"value": 3, "element": 502}, {"value": 2, "element": 150}, {"value": -2, "element": 158}, {"value": -6, "element": 166}]}], "team_h_difficulty": 4, "team_a_difficulty": 3, "pulse_id": 58938}, {"code": 2128326, "event": 5, "finished": true, "finished_provisional": true, "id": 39, "kickoff_time": "2020-10-17T14:00:00Z", "minutes": 90, "provisional_start_time": false, "started": true, "team_a": 16, "team_a_score": 3, "team_h": 5, "team_h_score": 3, "stats": [{"identifier": "goals_scored", "a": [{"value": 1, "element": 366}, {"value": 1, "element": 369}, {"value": 1, "element": 377}], "h": [{"value": 2, "element": 117}, {"value": 1, "element": 500}]}, {"identifier": "assists", "a": [{"value": 1, "element": 148}, {"value": 1, "element": 377}], "h": [{"value": 1, "element": 105}, {"value": 1, "element": 117}, {"value": 1, "element": 232}]}, {"identifier": "own_goals", "a": [], "h": []}, {"identifier": "penalties_saved", "a": [], "h": []}, {"identifier": "penalties_missed", "a": [], "h": []}, {"identifier": "yellow_cards", "a": [{"value": 1, "element": 364}], "h": [{"value": 1, "element": 232}]}, {"identifier": "red_cards", "a": [], "h": []}, {"identifier": "saves", "a": [{"value": 2, "element": 363}], "h": [{"value": 3, "element": 112}]}, {"identifier": "bonus", "a": [{"value": 2, "element": 377}, {"value": 1, "element": 366}], "h": [{"value": 3, "element": 117}]}, {"identifier": "bps", "a": [{"value": 41, "element": 377}, {"value": 27, "element": 366}, {"value": 24, "element": 369}, {"value": 21, "element": 148}, {"value": 14, "element": 370}, {"value": 12, "element": 376}, {"value": 11, "element": 375}, {"value": 10, "element": 363}, {"value": 7, "element": 364}, {"value": 5, "element": 362}, {"value": 5, "element": 365}, {"value": 3, "element": 565}, {"value": 2, "element": 361}, {"value": 2, "element": 524}], "h": [{"value": 63, "element": 117}, {"value": 25, "element": 232}, {"value": 25, "element": 500}, {"value": 23, "element": 105}, {"value": 15, "element": 110}, {"value": 15, "element": 116}, {"value": 12, "element": 112}, {"value": 10, "element": 102}, {"value": 10, "element": 113}, {"value": 6, "element": 119}, {"value": 6, "element": 120}, {"value": 4, "element": 114}, {"value": 3, "element": 118}, {"value": 2, "element": 123}]}], "team_h_difficulty": 2, "team_a_difficulty": 4, "pulse_id": 58936}, {"code": 2128331, "event": 5, "finished": true, "finished_provisional": true, "id": 44, "kickoff_time": "2020-10-17T16:30:00Z", "minutes": 90, "provisional_start_time": false, "started": true, "team_a": 1, "team_a_score": 0, "team_h": 12, "team_h_score": 1, "stats": [{"identifier": "goals_scored", "a": [], "h": [{"value": 1, "element": 276}]}, {"identifier": "assists", "a": [], "h": [{"value": 1, "element": 284}]}, {"identifier": "own_goals", "a": [], "h": []}, {"identifier": "penalties_saved", "a": [], "h": []}, {"identifier": "penalties_missed", "a": [], "h": []}, {"identifier": "yellow_cards", "a": [{"value": 1, "element": 567}], "h": [{"value": 1, "element": 277}, {"value": 1, "element": 279}, {"value": 1, "element": 286}, {"value": 1, "element": 556}]}, {"identifier": "red_cards", "a": [], "h": []}, {"identifier": "saves", "a": [{"value": 4, "element": 8}], "h": [{"value": 3, "element": 278}]}, {"identifier": "bonus", "a": [], "h": [{"value": 3, "element": 276}, {"value": 3, "element": 277}, {"value": 1, "element": 270}]}, {"identifier": "bps", "a": [{"value": 19, "element": 8}, {"value": 19, "element": 501}, {"value": 18, "element": 24}, {"value": 15, "element": 11}, {"value": 13, "element": 494}, {"value": 12, "element": 3}, {"value": 10, "element": 9}, {"value": 9, "element": 17}, {"value": 9, "element": 478}, {"value": 7, "element": 4}, {"value": 3, "element": 18}, {"value": 3, "element": 22}, {"value": 2, "element": 6}, {"value": 2, "element": 567}], "h": [{"value": 28, "element": 276}, {"value": 28, "element": 277}, {"value": 26, "element": 270}, {"value": 25, "element": 278}, {"value": 24, "element": 556}, {"value": 20, "element": 279}, {"value": 15, "element": 281}, {"value": 14, "element": 268}, {"value": 12, "element": 286}, {"value": 10, "element": 284}, {"value": 8, "element": 275}, {"value": 4, "element": 271}, {"value": 2, "element": 266}]}], "team_h_difficulty": 3, "team_a_difficulty": 5, "pulse_id": 58941}, {"code": 2128332, "event": 5, "finished": true, "finished_provisional": true, "id": 45, "kickoff_time": "2020-10-17T19:00:00Z", "minutes": 90, "provisional_start_time": false, "started": true, "team_a": 13, "team_a_score": 4, "team_h": 14, "team_h_score": 1, "stats": [{"identifier": "goals_scored", "a": [{"value": 1, "element": 298}, {"value": 1, "element": 302}, {"value": 1, "element": 306}, {"value": 1, "element": 313}], "h": []}, {"identifier": "assists", "a": [{"value": 2, "element": 306}, {"value": 1, "element": 290}, {"value": 1, "element": 302}], "h": [{"value": 1, "element": 333}]}, {"identifier": "own_goals", "a": [{"value": 1, "element": 300}], "h": []}, {"identifier": "penalties_saved", "a": [], "h": [{"value": 1, "element": 325}]}, {"identifier": "penalties_missed", "a": [{"value": 1, "element": 302}], "h": []}, {"identifier": "yellow_cards", "a": [{"value": 1, "element": 311}], "h": [{"value": 1, "element": 333}]}, {"identifier": "red_cards", "a": [], "h": []}, {"identifier": "saves", "a": [{"value": 4, "element": 291}], "h": [{"value": 8, "element": 325}]}, {"identifier": "bonus", "a": [{"value": 3, "element": 302}, {"value": 2, "element": 306}], "h": [{"value": 1, "element": 325}]}, {"identifier": "bps", "a": [{"value": 49, "element": 302}, {"value": 46, "element": 306}, {"value": 26, "element": 313}, {"value": 24, "element": 290}, {"value": 24, "element": 298}, {"value": 15, "element": 291}, {"value": 15, "element": 299}, {"value": 13, "element": 309}, {"value": 13, "element": 311}, {"value": 11, "element": 308}, {"value": 6, "element": 296}, {"value": 5, "element": 300}, {"value": 5, "element": 495}, {"value": 3, "element": 295}], "h": [{"value": 41, "element": 325}, {"value": 19, "element": 323}, {"value": 16, "element": 333}, {"value": 15, "element": 328}, {"value": 15, "element": 338}, {"value": 12, "element": 513}, {"value": 11, "element": 485}, {"value": 10, "element": 340}, {"value": 8, "element": 321}, {"value": 7, "element": 336}, {"value": 5, "element": 334}, {"value": 4, "element": 506}, {"value": 3, "element": 339}, {"value": 3, "element": 507}]}], "team_h_difficulty": 4, "team_a_difficulty": 2, "pulse_id": 58942}, {"code": 2128333, "event": 5, "finished": true, "finished_provisional": true, "id": 46, "kickoff_time": "2020-10-18T11:00:00Z", "minutes": 90, "provisional_start_time": false, "started": true, "team_a": 8, "team_a_score": 1, "team_h": 15, "team_h_score": 1, "stats": [{"identifier": "goals_scored", "a": [{"value": 1, "element": 557}], "h": [{"value": 1, "element": 343}]}, {"identifier": "assists", "a": [], "h": [{"value": 1, "element": 352}]}, {"identifier": "own_goals", "a": [], "h": []}, {"identifier": "penalties_saved", "a": [], "h": []}, {"identifier": "penalties_missed", "a": [{"value": 1, "element": 184}], "h": []}, {"identifier": "yellow_cards", "a": [{"value": 1, "element": 187}, {"value": 1, "element": 191}], "h": []}, {"identifier": "red_cards", "a": [], "h": []}, {"identifier": "saves", "a": [{"value": 5, "element": 516}], "h": [{"value": 5, "element": 483}]}, {"identifier": "bonus", "a": [{"value": 3, "element": 557}], "h": [{"value": 2, "element": 343}, {"value": 2, "element": 345}]}, {"identifier": "bps", "a": [{"value": 32, "element": 557}, {"value": 23, "element": 175}, {"value": 18, "element": 115}, {"value": 18, "element": 516}, {"value": 16, "element": 176}, {"value": 16, "element": 562}, {"value": 15, "element": 484}, {"value": 15, "element": 572}, {"value": 11, "element": 191}, {"value": 10, "element": 187}, {"value": 4, "element": 493}, {"value": -14, "element": 184}], "h": [{"value": 26, "element": 343}, {"value": 26, "element": 345}, {"value": 18, "element": 483}, {"value": 17, "element": 352}, {"value": 15, "element": 349}, {"value": 15, "element": 353}, {"value": 12, "element": 351}, {"value": 10, "element": 355}, {"value": 10, "element": 360}, {"value": 9, "element": 347}, {"value": 4, "element": 344}, {"value": 3, "element": 357}, {"value": 3, "element": 511}, {"value": 1, "element": 262}]}], "team_h_difficulty": 2, "team_a_difficulty": 2, "pulse_id": 58943}, {"code": 2128327, "event": 5, "finished": true, "finished_provisional": true, "id": 40, "kickoff_time": "2020-10-18T13:00:00Z", "minutes": 90, "provisional_start_time": false, "started": true, "team_a": 3, "team_a_score": 1, "team_h": 6, "team_h_score": 1, "stats": [{"identifier": "goals_scored", "a": [{"value": 1, "element": 80}], "h": [{"value": 1, "element": 141}]}, {"identifier": "assists", "a": [{"value": 1, "element": 78}], "h": [{"value": 1, "element": 108}]}, {"identifier": "own_goals", "a": [], "h": []}, {"identifier": "penalties_saved", "a": [], "h": []}, {"identifier": "penalties_missed", "a": [], "h": []}, {"identifier": "yellow_cards", "a": [{"value": 1, "element": 70}, {"value": 1, "element": 76}], "h": [{"value": 1, "element": 128}, {"value": 1, "element": 130}, {"value": 1, "element": 146}]}, {"identifier": "red_cards", "a": [{"value": 1, "element": 62}], "h": []}, {"identifier": "saves", "a": [], "h": [{"value": 2, "element": 128}]}, {"identifier": "bonus", "a": [{"value": 3, "element": 80}, {"value": 1, "element": 65}], "h": [{"value": 2, "element": 141}]}, {"identifier": "bps", "a": [{"value": 22, "element": 80}, {"value": 17, "element": 65}, {"value": 13, "element": 78}, {"value": 11, "element": 66}, {"value": 10, "element": 61}, {"value": 10, "element": 74}, {"value": 10, "element": 77}, {"value": 5, "element": 69}, {"value": 5, "element": 76}, {"value": 4, "element": 54}, {"value": 4, "element": 57}, {"value": 4, "element": 70}, {"value": 2, "element": 68}, {"value": 1, "element": 62}], "h": [{"value": 19, "element": 141}, {"value": 14, "element": 125}, {"value": 12, "element": 142}, {"value": 11, "element": 108}, {"value": 11, "element": 128}, {"value": 11, "element": 133}, {"value": 11, "element": 144}, {"value": 8, "element": 130}, {"value": 7, "element": 134}, {"value": 6, "element": 137}, {"value": 4, "element": 146}, {"value": 3, "element": 138}, {"value": 2, "element": 132}]}], "team_h_difficulty": 3, "team_a_difficulty": 3, "pulse_id": 58937}, {"code": 2128334, "event": 5, "finished": true, "finished_provisional": true, "id": 47, "kickoff_time": "2020-10-18T15:30:00Z", "minutes": 90, "provisional_start_time": false, "started": true, "team_a": 19, "team_a_score": 3, "team_h": 17, "team_h_score": 3, "stats": [{"identifier": "goals_scored", "a": [{"value": 1, "element": 439}, {"value": 1, "element": 443}], "h": [{"value": 2, "element": 388}, {"value": 1, "element": 390}]}, {"identifier": "assists", "a": [{"value": 1, "element": 435}, {"value": 1, "element": 558}], "h": [{"value": 1, "element": 388}, {"value": 1, "element": 390}, {"value": 1, "element": 542}]}, {"identifier": "own_goals", "a": [], "h": [{"value": 1, "element": 398}]}, {"identifier": "penalties_saved", "a": [], "h": []}, {"identifier": "penalties_missed", "a": [], "h": []}, {"identifier": "yellow_cards", "a": [{"value": 1, "element": 432}, {"value": 1, "element": 437}, {"value": 1, "element": 439}, {"value": 1, "element": 442}, {"value": 1, "element": 449}], "h": []}, {"identifier": "red_cards", "a": [], "h": []}, {"identifier": "saves", "a": [{"value": 3, "element": 431}], "h": [{"value": 2, "element": 383}]}, {"identifier": "bonus", "a": [{"value": 1, "element": 435}], "h": [{"value": 3, "element": 388}, {"value": 2, "element": 390}]}, {"identifier": "bps", "a": [{"value": 27, "element": 435}, {"value": 24, "element": 443}, {"value": 19, "element": 439}, {"value": 16, "element": 558}, {"value": 15, "element": 431}, {"value": 9, "element": 442}, {"value": 9, "element": 448}, {"value": 8, "element": 432}, {"value": 6, "element": 445}, {"value": 6, "element": 450}, {"value": 3, "element": 428}, {"value": 3, "element": 436}, {"value": 3, "element": 449}, {"value": -4, "element": 437}], "h": [{"value": 69, "element": 388}, {"value": 35, "element": 390}, {"value": 26, "element": 542}, {"value": 19, "element": 389}, {"value": 18, "element": 385}, {"value": 15, "element": 386}, {"value": 14, "element": 383}, {"value": 12, "element": 405}, {"value": 11, "element": 396}, {"value": 7, "element": 398}, {"value": 4, "element": 400}, {"value": 3, "element": 392}, {"value": 2, "element": 397}, {"value": -1, "element": 543}]}], "team_h_difficulty": 4, "team_a_difficulty": 4, "pulse_id": 58944}, {"code": 2128330, "event": 5, "finished": true, "finished_provisional": true, "id": 43, "kickoff_time": "2020-10-18T18:15:00Z", "minutes": 90, "provisional_start_time": false, "started": true, "team_a": 2, "team_a_score": 1, "team_h": 9, "team_h_score": 0, "stats": [{"identifier": "goals_scored", "a": [{"value": 1, "element": 106}], "h": []}, {"identifier": "assists", "a": [{"value": 1, "element": 38}], "h": []}, {"identifier": "own_goals", "a": [], "h": []}, {"identifier": "penalties_saved", "a": [], "h": []}, {"identifier": "penalties_missed", "a": [], "h": []}, {"identifier": "yellow_cards", "a": [{"value": 1, "element": 38}, {"value": 1, "element": 52}, {"value": 1, "element": 496}], "h": [{"value": 1, "element": 219}, {"value": 1, "element": 228}, {"value": 1, "element": 229}, {"value": 1, "element": 498}]}, {"identifier": "red_cards", "a": [], "h": []}, {"identifier": "saves", "a": [{"value": 5, "element": 12}], "h": [{"value": 3, "element": 217}]}, {"identifier": "bonus", "a": [{"value": 3, "element": 106}, {"value": 2, "element": 12}, {"value": 1, "element": 41}, {"value": 1, "element": 496}], "h": []}, {"identifier": "bps", "a": [{"value": 31, "element": 106}, {"value": 30, "element": 12}, {"value": 26, "element": 41}, {"value": 26, "element": 496}, {"value": 22, "element": 42}, {"value": 20, "element": 46}, {"value": 15, "element": 37}, {"value": 14, "element": 38}, {"value": 9, "element": 40}, {"value": 8, "element": 52}, {"value": 2, "element": 540}, {"value": 1, "element": 514}], "h": [{"value": 20, "element": 561}, {"value": 15, "element": 217}, {"value": 13, "element": 518}, {"value": 11, "element": 239}, {"value": 10, "element": 219}, {"value": 8, "element": 228}, {"value": 8, "element": 235}, {"value": 5, "element": 229}, {"value": 5, "element": 234}, {"value": 5, "element": 498}, {"value": 3, "element": 233}, {"value": 3, "element": 579}, {"value": 2, "element": 225}, {"value": 2, "element": 231}]}], "team_h_difficulty": 2, "team_a_difficulty": 4, "pulse_id": 58940}, {"code": 2128335, "event": 5, "finished": true, "finished_provisional": true, "id": 48, "kickoff_time": "2020-10-19T16:30:00Z", "minutes": 90, "provisional_start_time": false, "started": true, "team_a": 4, "team_a_score": 0, "team_h": 18, "team_h_score": 0, "stats": [{"identifier": "goals_scored", "a": [], "h": []}, {"identifier": "assists", "a": [], "h": []}, {"identifier": "own_goals", "a": [], "h": []}, {"identifier": "penalties_saved", "a": [], "h": []}, {"identifier": "penalties_missed", "a": [], "h": []}, {"identifier": "yellow_cards", "a": [{"value": 1, "element": 89}, {"value": 1, "element": 97}], "h": [{"value": 1, "element": 409}, {"value": 1, "element": 411}]}, {"identifier": "red_cards", "a": [], "h": []}, {"identifier": "saves", "a": [{"value": 6, "element": 96}], "h": [{"value": 4, "element": 417}]}, {"identifier": "bonus", "a": [{"value": 3, "element": 96}, {"value": 1, "element": 85}], "h": [{"value": 2, "element": 417}, {"value": 1, "element": 418}, {"value": 1, "element": 422}]}, {"identifier": "bps", "a": [{"value": 34, "element": 96}, {"value": 26, "element": 85}, {"value": 25, "element": 81}, {"value": 22, "element": 83}, {"value": 17, "element": 97}, {"value": 15, "element": 100}, {"value": 12, "element": 89}, {"value": 11, "element": 98}, {"value": 7, "element": 90}, {"value": 3, "element": 86}, {"value": 3, "element": 87}, {"value": 3, "element": 95}, {"value": -8, "element": 91}], "h": [{"value": 32, "element": 417}, {"value": 26, "element": 418}, {"value": 26, "element": 422}, {"value": 25, "element": 530}, {"value": 24, "element": 414}, {"value": 15, "element": 481}, {"value": 10, "element": 544}, {"value": 10, "element": 555}, {"value": 6, "element": 409}, {"value": 5, "element": 582}, {"value": 4, "element": 446}, {"value": 1, "element": 358}, {"value": 1, "element": 413}, {"value": -1, "element": 411}]}], "team_h_difficulty": 2, "team_a_difficulty": 2, "pulse_id": 58945}, {"code": 2128329, "event": 5, "finished": true, "finished_provisional": true, "id": 42, "kickoff_time": "2020-10-19T19:00:00Z", "minutes": 90, "provisional_start_time": false, "started": true, "team_a": 20, "team_a_score": 1, "team_h": 10, "team_h_score": 0, "stats": [{"identifier": "goals_scored", "a": [{"value": 1, "element": 460}], "h": []}, {"identifier": "assists", "a": [{"value": 1, "element": 470}], "h": []}, {"identifier": "own_goals", "a": [], "h": []}, {"identifier": "penalties_saved", "a": [], "h": []}, {"identifier": "penalties_missed", "a": [], "h": []}, {"identifier": "yellow_cards", "a": [{"value": 1, "element": 454}], "h": [{"value": 1, "element": 197}, {"value": 1, "element": 204}]}, {"identifier": "red_cards", "a": [], "h": []}, {"identifier": "saves", "a": [{"value": 2, "element": 455}], "h": [{"value": 2, "element": 213}]}, {"identifier": "bonus", "a": [{"value": 3, "element": 470}, {"value": 2, "element": 460}, {"value": 1, "element": 461}], "h": []}, {"identifier": "bps", "a": [{"value": 37, "element": 470}, {"value": 32, "element": 460}, {"value": 26, "element": 461}, {"value": 25, "element": 455}, {"value": 24, "element": 546}, {"value": 23, "element": 459}, {"value": 20, "element": 458}, {"value": 13, "element": 464}, {"value": 5, "element": 454}, {"value": 5, "element": 465}, {"value": 5, "element": 474}, {"value": 4, "element": 466}, {"value": 2, "element": 469}, {"value": 2, "element": 505}], "h": [{"value": 16, "element": 491}, {"value": 14, "element": 200}, {"value": 12, "element": 211}, {"value": 12, "element": 213}, {"value": 11, "element": 197}, {"value": 11, "element": 203}, {"value": 11, "element": 492}, {"value": 10, "element": 198}, {"value": 6, "element": 204}, {"value": 3, "element": 202}, {"value": 3, "element": 205}, {"value": 3, "element": 570}, {"value": 2, "element": 193}, {"value": -1, "element": 209}]}], "team_h_difficulty": 2, "team_a_difficulty": 3, "pulse_id": 58939}]